packrect-1.0.5.dist-info/RECORD
packrect-1.0.5.dist-info/WHEEL
packrect-1.0.5.dist-info/top_level.txt
packrect-1.0.5.dist-info/METADATA
packrect/packrect.cpython-39-darwin.so
packrect/__init__.py
packrect/packrect.pyi
packrect/py.typed
